max/_core/__init__.pyi
max/_core/dialects/__init__.pyi
max/_core/dialects/builtin/__init__.pyi
max/_core/dialects/builtin/passes.pyi
max/_core/dialects/kgen.pyi
max/_core/dialects/m.pyi
max/_core/dialects/mo/__init__.pyi
max/_core/dialects/mo/passes.pyi
max/_core/dialects/mosh.pyi
max/_core/dialects/rmo/__init__.pyi
max/_core/dialects/rmo/passes.pyi
max/_core/driver.pyi
max/_core/dtype.pyi
max/_core/engine.pyi
max/_core/graph.pyi
max/_core/nixl.pyi
max/_core/profiler.pyi
max/_core/safetensors.pyi
max/_core/xxhash.pyi
max/_core_mojo/__init__.py
max/_core_mojo/mojo_module.mojo
max/_core_types/driver.py
max/_mlir/_mlir_libs/__init__.py
max/_mlir/_mlir_libs/_mlir/__init__.pyi
max/_mlir/_mlir_libs/_mlir/ir.pyi
max/_mlir/_mlir_libs/_mlir/passmanager.pyi
max/_mlir/_mlir_libs/_mlir/rewrite.pyi
max/_mlir/dialects/_ods_common.py
max/_mlir/dialects/mo.py
max/_mlir/dialects/rmo.py
max/_mlir/ir.py
max/_passes.py
max/_realization_context.py
max/_support.py
max/_tensor_repr.py
max/benchmark/benchmark_serving.py
max/benchmark/benchmark_shared/__init__.py
max/benchmark/benchmark_shared/config.py
max/benchmark/benchmark_shared/cpu_metrics.py
max/benchmark/benchmark_shared/datasets/__init__.py
max/benchmark/benchmark_shared/datasets/arxiv_summarization.py
max/benchmark/benchmark_shared/datasets/axolotl.py
max/benchmark/benchmark_shared/datasets/batch_job.py
max/benchmark/benchmark_shared/datasets/code_debug.py
max/benchmark/benchmark_shared/datasets/huggingface.py
max/benchmark/benchmark_shared/datasets/interface.py
max/benchmark/benchmark_shared/datasets/local.py
max/benchmark/benchmark_shared/datasets/obfuscated_conversations.py
max/benchmark/benchmark_shared/datasets/packaged_data/axolotl_dummy.json
max/benchmark/benchmark_shared/datasets/packaged_data/sonnet_4x.txt
max/benchmark/benchmark_shared/datasets/random.py
max/benchmark/benchmark_shared/datasets/registry.py
max/benchmark/benchmark_shared/datasets/sharegpt.py
max/benchmark/benchmark_shared/datasets/sonnet.py
max-26.1.0.dist-info/WHEEL
max-26.1.0.dist-info/METADATA
max-26.1.0.dist-info/entry_points.txt
max-26.1.0.dist-info/LICENSE
max-26.1.0.dist-info/Third-Party-Notices
max-26.1.0.dist-info/RECORD
